python_anesthesia_simulator/__init__.py
python_anesthesia_simulator/disturbances.py
python_anesthesia_simulator/metrics.py
python_anesthesia_simulator/pd_models.py
python_anesthesia_simulator/pk_models.py
python_anesthesia_simulator/simulator.py
python_anesthesia_simulator-1.0.0.dist-info/METADATA
python_anesthesia_simulator-1.0.0.dist-info/WHEEL
python_anesthesia_simulator-1.0.0.dist-info/licenses/LICENSE
python_anesthesia_simulator-1.0.0.dist-info/RECORD
