Metadata-Version: 2.4
Name: python_anesthesia_simulator
Version: 1.0.0
Summary: Anesthesia simulator: modellize the effect of drugs (Propofol, Remifentanil, Norepinephrine) during general anesthesia. Specially build for control design.
Project-URL: Homepage, https://github.com/BobAubouin/Python_Anesthesia_Simulator
Project-URL: Bug Tracker, https://github.com/BobAubouin/Python_Anesthesia_Simulator/issues
Author: Bob Aubouin--Pairault
Author-email: bob.aubouin@tutanota.com
License: GNU General Public License v3 (GPLv3)
License-File: LICENSE
Classifier: License :: OSI Approved :: GNU General Public License v3 (GPLv3)
Classifier: Operating System :: OS Independent
Classifier: Programming Language :: Python :: 3
Requires-Python: >=3.9
Requires-Dist: casadi>=3.6.3
Requires-Dist: control==0.9.4
Requires-Dist: matplotlib
Requires-Dist: numpy
Requires-Dist: pandas
